todowrite/__init__.py
todowrite/py.typed
todowrite/version.py
todowrite/core/__init__.py
todowrite/core/app.py
todowrite/core/app_node_updater.py
todowrite/core/constants.py
todowrite/core/exceptions.py
todowrite/core/project_manager.py
todowrite/core/schema.py
todowrite/core/types.py
todowrite/core/utils.py
todowrite/core/schemas/__init__.py
todowrite/core/schemas/todowrite.schema.json
todowrite/database/__init__.py
todowrite/database/config.py
todowrite/database/models.py
todowrite/storage/__init__.py
todowrite/storage/schema_validator.py
todowrite/storage/yaml_manager.py
todowrite/storage/yaml_storage.py
todowrite/tools/__init__.py
todowrite/tools/extract_schema.py
todowrite/tools/git-commit-msg-hook.sh
todowrite/tools/tw_lint_soc.py
todowrite/tools/tw_stub_command.py
todowrite/tools/tw_trace.py
todowrite/tools/tw_validate.py
todowrite-0.4.1.dist-info/METADATA
todowrite-0.4.1.dist-info/WHEEL
todowrite-0.4.1.dist-info/licenses/LICENSE
todowrite-0.4.1.dist-info/RECORD
