Metadata-Version: 2.4
Name: todowrite
Version: 0.4.1
Summary: A Python library for managing complex software projects with Goals, Tasks, Concepts, and Commands
Project-URL: Homepage, https://github.com/dderyldowney/todowrite
Project-URL: Repository, https://github.com/dderyldowney/todowrite.git
Project-URL: Documentation, https://github.com/dderyldowney/todowrite/blob/main/README.md
Project-URL: Bug Tracker, https://github.com/dderyldowney/todowrite/issues
Author-email: D Deryl Downey <dderyldowney@gmail.com>
License: MIT
License-File: LICENSE
Keywords: api,commands,concepts,goals,management,project,task,tasks,todo
Classifier: Development Status :: 4 - Beta
Classifier: Intended Audience :: Developers
Classifier: License :: OSI Approved :: MIT License
Classifier: Programming Language :: Python :: 3
Classifier: Programming Language :: Python :: 3.12
Classifier: Programming Language :: Python :: 3.13
Classifier: Topic :: Software Development :: Libraries :: Python Modules
Classifier: Topic :: Utilities
Requires-Python: >=3.12
Requires-Dist: jsonschema>=4.0.0
Requires-Dist: pyyaml>=6.0
Requires-Dist: sqlalchemy>=2.0.0
Provides-Extra: dev
Requires-Dist: pre-commit>=3.0.0; extra == 'dev'
Requires-Dist: pytest-cov>=4.0.0; extra == 'dev'
Requires-Dist: pytest>=7.0.0; extra == 'dev'
Requires-Dist: ruff>=0.7.0; extra == 'dev'
Provides-Extra: postgres
Requires-Dist: psycopg2-binary>=2.9.0; extra == 'postgres'
